positionport/__init__.py
positionport/core.py
positionport-0.1.2.dist-info/METADATA
positionport-0.1.2.dist-info/WHEEL
positionport-0.1.2.dist-info/top_level.txt
positionport-0.1.2.dist-info/RECORD
