Metadata-Version: 2.4
Name: positionport
Version: 0.1.2
Summary: Official client library for PositionPort API
Author-email: James <devgsbmaster@gmail.com>
License: MIT
Project-URL: Homepage, https://github.com/PositionPort
Project-URL: Repository, https://github.com/PositionPort/positionport_pypl
Project-URL: Issues, https://github.com/PositionPort/positionport_pypl/issues
Keywords: positionport,trading,api,client,portfolio,risk
Requires-Python: >=3.7
Requires-Dist: requests>=2.25.0
